ps_request/__init__.py
ps_request/database.py
ps_request/request.py
ps_database-0.3.dist-info/METADATA
ps_database-0.3.dist-info/WHEEL
ps_database-0.3.dist-info/licence
ps_database-0.3.dist-info/top_level.txt
ps_database-0.3.dist-info/RECORD
