Metadata-Version: 2.1
Name: ps-database
Version: 0.3
License-File: licence
Requires-Dist: requests
